{
  "passThreshold": 0.8,
  "questions": [
    {
      "id": "q1",
      "type": "single",
      "scenario": "The Orders API has `vpc-orders-prod` with a subnet in `us-central1`. The team adds a worker in `europe-west2`. What is a reasonable GCP network move?",
      "options": [
        { "id": "a", "text": "Create a regional subnet in `europe-west2` in the same VPC network if the design calls for shared network scope." },
        { "id": "b", "text": "Assume the `us-central1` subnet automatically places resources in every region." },
        { "id": "c", "text": "Create a billing account for each subnet." },
        { "id": "d", "text": "Use IAM roles as IP ranges." }
      ],
      "correct": ["a"],
      "explanation": "A GCP VPC network is global, but subnets are regional. A new region needs an appropriate regional subnet."
    },
    {
      "id": "q2",
      "type": "single",
      "scenario": "Which statement best compares AWS and GCP at the basic VPC level?",
      "options": [
        { "id": "a", "text": "An AWS VPC is regional; a GCP VPC network is global with regional subnets." },
        { "id": "b", "text": "Both providers make subnets global resources." },
        { "id": "c", "text": "A GCP VPC network is the same thing as a folder." },
        { "id": "d", "text": "AWS and GCP networking scopes never matter." }
      ],
      "correct": ["a"],
      "explanation": "This scope difference is one of the first GCP networking surprises for AWS learners."
    },
    {
      "id": "q3",
      "type": "multiple",
      "scenario": "What remains regional even when the VPC network is global?",
      "options": [
        { "id": "a", "text": "Subnet IP ranges." },
        { "id": "b", "text": "Many workloads and managed resources." },
        { "id": "c", "text": "Latency and placement decisions." },
        { "id": "d", "text": "The fact that every resource has the same region." }
      ],
      "correct": ["a", "b", "c"],
      "explanation": "Global VPC scope does not erase regional placement, latency, or service design."
    }
  ]
}
