{
  "passThreshold": 0.8,
  "questions": [
    {
      "id": "q1",
      "type": "single",
      "scenario": "A cleanup script can permanently delete production receipt objects with a broad role. What is the safe-deletion concern?",
      "options": [
        { "id": "a", "text": "One script or typo can remove important data before recovery is possible." },
        { "id": "b", "text": "Receipts cannot live in Cloud Storage." },
        { "id": "c", "text": "Backups make IAM irrelevant." },
        { "id": "d", "text": "Deletion should be impossible for every data type forever." }
      ],
      "correct": ["a"],
      "explanation": "Safe deletion uses permissions, delays, retention, and logging to reduce irreversible mistakes."
    },
    {
      "id": "q2",
      "type": "single",
      "scenario": "The business has a legal requirement to delete some customer data after a period. What is the healthy goal?",
      "options": [
        { "id": "a", "text": "Make deletion deliberate and policy-driven, not accidental." },
        { "id": "b", "text": "Never delete anything under any circumstances." },
        { "id": "c", "text": "Let any developer delete all production data." },
        { "id": "d", "text": "Hide deletion from logs." }
      ],
      "correct": ["a"],
      "explanation": "Safe deletion does not mean no deletion; it means controlled deletion."
    },
    {
      "id": "q3",
      "type": "multiple",
      "scenario": "Which controls can support safe deletion?",
      "options": [
        { "id": "a", "text": "Narrow IAM permissions." },
        { "id": "b", "text": "Retention or soft-delete windows where appropriate." },
        { "id": "c", "text": "Deletion logging and approval for sensitive data." },
        { "id": "d", "text": "Broad delete access for every automation." }
      ],
      "correct": ["a", "b", "c"],
      "explanation": "Safe deletion is a set of controls around destructive actions."
    }
  ]
}
